MJOLNIR/CalibrationBambus.csv
MJOLNIR/CalibrationFlatCone.csv
MJOLNIR/CalibrationMultiFLEXX.csv
MJOLNIR/Marray.py
MJOLNIR/Normalization_1.calib
MJOLNIR/Normalization_2.calib
MJOLNIR/Normalization_3.calib
MJOLNIR/Normalization_4.calib
MJOLNIR/Normalization_5.calib
MJOLNIR/Normalization_6.calib
MJOLNIR/Normalization_7.calib
MJOLNIR/Normalization_8.calib
MJOLNIR/TasUBlibDEG.py
MJOLNIR/__init__.py
MJOLNIR/_interactiveSettings.py
MJOLNIR/_tools.py
MJOLNIR/CommandLineScripts/MJOLNIR3DView.py
MJOLNIR/CommandLineScripts/MJOLNIRCalibrationInspector.py
MJOLNIR/CommandLineScripts/MJOLNIRConvert.py
MJOLNIR/CommandLineScripts/MJOLNIRHistory.py
MJOLNIR/CommandLineScripts/__init__.py
MJOLNIR/CommandLineScripts/_tools.py
MJOLNIR/CommandLineScripts/test_commandline.py
MJOLNIR/Data/BackgroundModel.py
MJOLNIR/Data/DataFile.py
MJOLNIR/Data/DataSet.py
MJOLNIR/Data/DraggableShapes.py
MJOLNIR/Data/Mask.py
MJOLNIR/Data/RLUAxes.py
MJOLNIR/Data/Sample.py
MJOLNIR/Data/Viewer1D.py
MJOLNIR/Data/Viewer3D.py
MJOLNIR/Data/Viewer3DPyQtGraph.py
MJOLNIR/Data/__init__.py
MJOLNIR/Data/scissors.png
MJOLNIR/Geometry/Analyser.py
MJOLNIR/Geometry/Detector.py
MJOLNIR/Geometry/GeometryConcept.py
MJOLNIR/Geometry/Instrument.py
MJOLNIR/Geometry/InstrumentXML.py
MJOLNIR/Geometry/Wedge.py
MJOLNIR/Geometry/__init__.py
MJOLNIR/Geometry/detsequence.dat
MJOLNIR/Geometry/eck_Flipped.py
MJOLNIR/Geometry/reso.py
MJOLNIR/Statistics/CutObject.py
MJOLNIR/Statistics/FittingFunction.py
MJOLNIR/Statistics/__init__.py
mjolnir-1.3.5.dist-info/licenses/LICENSE.txt
mjolnir-1.3.5.dist-info/METADATA
mjolnir-1.3.5.dist-info/WHEEL
mjolnir-1.3.5.dist-info/dependency_links.txt
mjolnir-1.3.5.dist-info/entry_points.txt
mjolnir-1.3.5.dist-info/top_level.txt
mjolnir-1.3.5.dist-info/RECORD
